{
  "schemaVersion": "viewloom-12a4-category-execution-cost-probe-execution-contract-v1",
  "workstream": "12A-4-6 provider-separated bounded category execution-cost production package",
  "status": "accepted_and_retired",
  "trackingIssue": 519,
  "acceptedImplementation": {
    "packagePr": 547,
    "executionHardeningPr": 551,
    "d1CompatibilityFixPr": 555,
    "validatedImplementationHeadSha": "6ebdee7053e9b94b62d21bda5a4572aa925a7555",
    "mergeSha": "003d4988df821294fd33fc3e0f8ed38da00af4cf",
    "productionJobSkippedOnPullRequest": true,
    "readinessRetryValidated": true,
    "explicitAttemptStateValidated": true,
    "missingMeasurementsPreserved": true,
    "d1CompatibleDictionaryUpsertValidated": true
  },
  "acceptedMeasurement": {
    "attempt": 3,
    "runId": "category-cost-probe-attempt-3",
    "triggerPr": 557,
    "triggerHeadSha": "6228412ddbb202691c69a2313e6cb753c1d11053",
    "triggerMergeSha": "741e080187cfc3c92595120e57899d52664dd85e",
    "acceptancePr": 558,
    "acceptanceMergeSha": "7e272dcf831b1f3a3f331efa94996115d84f1add",
    "evidence": "docs/audits/12a4-category-execution-cost-probe-attempt-3-evidence.json",
    "sourceWorkflowRunId": 29358245194,
    "sourceArtifactId": 8321254541,
    "acceptanceArtifactId": 8321258554,
    "providerOrder": ["twitch", "kick"],
    "twitchGatePass": true,
    "kickGatePass": true,
    "allReservedRowsRemoved": true,
    "providerLeakageRowsZero": true,
    "temporaryWorkersDeleted": true,
    "categoryCaptureRemainedDisabled": true,
    "runtimeCaptureEnablementAuthorized": false
  },
  "measurements": {
    "twitch": {
      "categoryGeneratorQueries": 4,
      "d1Statements": 10,
      "d1RowsRead": 7,
      "d1RowsWritten": 10,
      "d1Changes": 6,
      "d1SqlDurationMs": 1.743,
      "workerWallMs": 2010,
      "collectorLatencyDeltaMs": 942,
      "databaseSizeDeltaBytes": 0,
      "probeCleanupRemainingRows": 0,
      "providerLeakageRows": 0
    },
    "kick": {
      "categoryGeneratorQueries": 4,
      "d1Statements": 10,
      "d1RowsRead": 7,
      "d1RowsWritten": 10,
      "d1Changes": 6,
      "d1SqlDurationMs": 1.417,
      "workerWallMs": 1760,
      "collectorLatencyDeltaMs": 9,
      "databaseSizeDeltaBytes": 0,
      "probeCleanupRemainingRows": 0,
      "providerLeakageRows": 0
    }
  },
  "retirement": {
    "triggerStatus": "consumed_and_retired",
    "productionPushTriggerPresent": false,
    "productionJobPresent": false,
    "cloudflareSecretsReferenced": false,
    "productionWorkerDeployPresent": false,
    "verificationOnlyWorkflow": true,
    "rearmAuthorized": false
  },
  "historicalExecutionBoundary": {
    "reservedProbeIdentifiersOnly": true,
    "fixedHistoricalProbeDay": "1900-01-02",
    "providerSeparated": true,
    "stopBeforeKickOnTwitchFailure": true,
    "cleanupInFinally": true,
    "remoteSchemaApply": false,
    "categoryCaptureEnablement": false,
    "persistentProductionCategoryRows": false,
    "newCron": false,
    "backfill": false,
    "rawRetentionChange": false,
    "categoryAnalyticsUi": false,
    "crossProviderCategoryIdentity": false,
    "combinedProviderCategoryRanking": false
  },
  "requiredSecrets": [],
  "nextGate": "provider-separated category capture enablement decision using the accepted production cost evidence; runtime capture remains disabled until a separate accepted gate"
}
